Workbook
Name LandPrice: Inputs!$B$5
Name LandClosing: Inputs!$B$6
Name LandLtv: Inputs!$B$8
Name LandRate: Inputs!$B$9
Name LandPointsPct: Inputs!$B$10
Name TaxRate: Inputs!$B$11
Name HoaMonthly: Inputs!$B$12
Name PreConMonths: Inputs!$B$15
Name BuildMonths: Inputs!$B$16
Name ListEarlyMonths: Inputs!$B$17
Name ClosingDays: Inputs!$B$18
Name MonthDays: Inputs!$B$19
Name Ltc: Inputs!$B$22
Name LoanRate: Inputs!$B$23
Name PointsPct: Inputs!$B$24
Name DrawFee: Inputs!$B$25
Name TermMonths: Inputs!$B$26
Name ExtensionPct: Inputs!$B$27
Name ExtensionMonths: Inputs!$B$28
Name InterestMode: Inputs!$B$29
Name InsuranceRate: Inputs!$B$32
Name UtilBuild: Inputs!$B$33
Name UtilAfter: Inputs!$B$34
Name StagingMonthly: Inputs!$B$35
Name UpkeepMonthly: Inputs!$B$36
Name ListingPct: Inputs!$B$39
Name BuyerPct: Inputs!$B$40
Name ClosingPct: Inputs!$B$41
Name Concessions: Inputs!$B$42
Name BidSubtotal: Inputs!$G$32
Name ContingencyPct: Inputs!$G$33
Name Contingency: Inputs!$G$34
Name EstimateTotal: Inputs!$G$35
Name SoftCost: Inputs!$G$36
Name HardCost: Inputs!$G$37
Name colK: 'base'!$A$65:$A$79
Name colOvBuildClose: 'base'!$B$65:$B$79
Name colOvAll: 'base'!$C$65:$C$79
Name colOvBuild: 'base'!$D$65:$D$79
Name colOvAfter: 'base'!$E$65:$E$79
Name colOvListed: 'base'!$F$65:$F$79
Name colSine: 'base'!$G$65:$G$79
Name colDraw: 'base'!$H$65:$H$79
Name colSpend: 'base'!$I$65:$I$79
Name colSpendBefore: 'base'!$J$65:$J$79
Name colDrawnBefore: 'base'!$K$65:$K$79
Name colEqFirst: 'base'!$L$65:$L$79
Name colLoanDraw: 'base'!$M$65:$M$79
Name colEquitySpend: 'base'!$N$65:$N$79
Name colSpendThrough: 'base'!$O$65:$O$79
Name colDrawnThrough: 'base'!$P$65:$P$79
Name colBalanceStart: 'base'!$Q$65:$Q$79
Name colPoints: 'base'!$R$65:$R$79
Name colDrawFee: 'base'!$S$65:$S$79
Name colInterest: 'base'!$T$65:$T$79
Name colInterestPaid: 'base'!$U$65:$U$79
Name colInterestCap: 'base'!$V$65:$V$79
Name colBalanceEnd: 'base'!$W$65:$W$79
Name colLandInterest: 'base'!$X$65:$X$79
Name colExtensionFee: 'base'!$Y$65:$Y$79

Sheet Inputs
A1: Golden deal - inputs
A2: Money in dollars, rates as decimals. Source: src/engine/__fixtures__/golden-deal.inputs.json
A4: Lot | E4: Estimate (bids)
A5: Land price | B5: 295000 | E5: Code | F5: Division | G5: Amount
A6: Land closing costs | B6: 4000 | E6: plans | F6: soft | G6: 8500
A7: Land financing | B7: cash | E7: permits | F7: soft | G7: 26800
A8: Land loan LTV | B8: 0 | C8: 0 when bought for cash | E8: surveySoils | F8: soft | G8: 3200
A9: Land loan rate (annual) | B9: 0 | E9: excavation | F9: hard | G9: 22000
A10: Land loan points | B10: 0 | E10: utilities | F10: hard | G10: 15500
A11: Property tax rate (annual) | B11: 0.0048 | E11: foundation | F11: hard | G11: 62000
A12: HOA per month | B12: 0 | E12: framing | F12: hard | G12: 108000
E13: roofing | F13: hard | G13: 24000
A14: Timeline (months from land close) | E14: windows | F14: hard | G14: 31000
A15: Pre-construction months (P) | B15: 2 | E15: cladding | F15: hard | G15: 38000
A16: Build months (B) | B16: 9 | E16: insulation | F16: hard | G16: 10500
A17: List early months (L) | B17: 0 | E17: plumbing | F17: hard | G17: 33000
A18: Closing days after contract | B18: 35 | E18: electrical | F18: hard | G18: 29700
A19: Days per month | B19: =365/12 | E19: hvac | F19: hard | G19: 26500
E20: drywall | F20: hard | G20: 30000
A21: Construction loan | E21: trim | F21: hard | G21: 24500
A22: Loan-to-cost | B22: 0.8 | E22: cabinets | F22: hard | G22: 54000
A23: Rate (annual) | B23: 0.09 | E23: flooring | F23: hard | G23: 31000
A24: Points | B24: 0.01 | E24: paint | F24: hard | G24: 18000
A25: Draw fee per draw | B25: 200 | E25: fixtures | F25: hard | G25: 24000
A26: Term months (from build start) | B26: 12 | E26: garageDoors | F26: hard | G26: 6800
A27: Extension fee | B27: 0.005 | C27: of the commitment, per extension | E27: flatwork | F27: hard | G27: 16500
A28: Extension months | B28: 3 | E28: landscaping | F28: hard | G28: 20000
A29: Interest mode | B29: paid | C29: paid | capitalized | E29: cleaning | F29: hard | G29: 4150
E30: supervision | F30: hard | G30: 33300
A31: Carry
A32: Builder's risk insurance (annual, of estimate) | B32: 0.0035 | E32: Bid subtotal | G32: =SUM(G6:G30)
A33: Utilities per month, during build | B33: 150 | E33: Contingency rate | G33: 0.05
A34: Utilities per month, after completion | B34: 250 | E34: Contingency | G34: =ROUND(BidSubtotal*ContingencyPct,2)
A35: Staging per month, while listed | B35: 500 | E35: Estimate total | G35: =BidSubtotal+Contingency
A36: Upkeep per month, after completion | B36: 100 | E36: Soft costs (division soft) | G36: =SUMIF(F6:F30,"soft",G6:G30)
E37: Hard costs (incl. contingency) | G37: =EstimateTotal-SoftCost
A38: Selling
A39: Listing commission | B39: 0.025
A40: Buyer-agent commission | B40: 0.025
A41: Closing and title | B41: 0.01
A42: Concessions | B42: 15000
A44: Scenarios
A45: Scenario | B45: Sale price | C45: Days on market | D45: Overrun
A46: base | B46: 1350000 | C46: 62 | D46: 0
A47: stress | B47: 1255500 | C47: 400 | D47: 0.05

Sheet base
A1: Golden deal - base scenario
A2: Every value below is a formula implementing the Reference cash-flow algorithm (dollars).
A4: Scenario inputs
A5: Sale price | B5: =Inputs!$B$46
A6: Days on market | B6: =Inputs!$C$46
A7: Cost overrun | B7: =Inputs!$D$46
A9: Times (months) - Reference step 1
A10: Build start = P | B10: =PreConMonths
A11: Completion = P + B | B11: =BuildStart+BuildMonths
A12: List = completion - L | B12: =Completion-ListEarlyMonths
A13: Contract = list + DOM / MONTH_DAYS | B13: =ListMonth+DomDays/MonthDays
A14: Sale close = max(contract + closingDays / MONTH_DAYS, completion) | B14: =MAX(Contract+ClosingDays/MonthDays,Completion)
A15: Loan maturity = build start + term | B15: =BuildStart+TermMonths
A16: Periods N = ceil(sale close) | B16: =CEILING(SaleClose,1)
A17: Period rows in this sheet | B17: =COUNT(colK)
A19: Costs and loan - Reference steps 2-8
A20: Soft actual = round(soft x (1 + overrun)) | B20: =ROUND(SoftCost*(1+Overrun),2)
A21: Hard actual = round(hard x (1 + overrun)) | B21: =ROUND(HardCost*(1+Overrun),2)
A22: Sum of draw sines | B22: =SUM(colSine)
A23: Loan commitment = round(LTC x estimate total) | B23: =ROUND(Ltc*EstimateTotal,2)
A24: Equity requirement = estimate total - commitment | B24: =EstimateTotal-Commitment
A25: Construction points = round(points x commitment) | B25: =IF(Commitment>0,ROUND(PointsPct*Commitment,2),0)
A26: Land loan = round(LTV x land price) | B26: =ROUND(LandLtv*LandPrice,2)
A27: Land points = round(points x land loan) | B27: =ROUND(LandPointsPct*LandLoan,2)
A28: Extensions n | B28: =IF(AND(Commitment>0,SaleClose>Maturity),CEILING((SaleClose-Maturity)/ExtensionMonths,1),0)
A29: Extension fee each = round(extension % x commitment) | B29: =ROUND(ExtensionPct*Commitment,2)
A30: Interest capitalized (1 = yes) | B30: =IF(InterestMode="capitalized",1,0)
A32: Sale (at sale close, booked on period N-1) - Reference step 11
A33: Commissions = round(price x (listing + buyer)) | B33: =ROUND(SalePrice*(ListingPct+BuyerPct),2)
A34: Closing = round(price x closing %) | B34: =ROUND(SalePrice*ClosingPct,2)
A35: Concessions | B35: =Concessions
A36: Net = price - commissions - closing - concessions | B36: =SalePrice-Commissions-SaleClosing-SaleConcessions
A37: Loan drawn | B37: =SUM(colLoanDraw)
A38: Capitalized interest | B38: =SUM(colInterestCap)
A39: Loan payoff = drawn + capitalized interest + land loan | B39: =LoanDrawn+CapInterest+LandLoan
A40: Equity return = net - payoff | B40: =NetProceeds-Payoff
A42: Totals and metrics - Reference steps 12-15
A43: Build spent = soft actual + hard actual | B43: =SoftActual+HardActual
A44: Financing | B44: =SUM(colPoints)+LandPoints+SUM(colInterest)+SUM(colLandInterest)+SUM(colDrawFee)+SUM(colExtensionFee)
A45: Carry | B45: =SUM(colTax)+SUM(colInsurance)+SUM(colUtilities)+SUM(colStaging)+SUM(colUpkeep)+SUM(colHoa)
A46: Total project cost | B46: =LandPrice+LandClosing+BuildSpent+Financing+Carry
A47: Selling costs | B47: =Commissions+SaleClosing+SaleConcessions
A48: Profit | B48: =SalePrice-SellingCosts-TotalProjectCost
A49: Peak cash | B49: =MAX(colCumEquity)
A50: Break-even sale price | B50: =ROUND((TotalProjectCost+Concessions)/(1-ListingPct-BuyerPct-ClosingPct),2)
A51: Loan balance after period completion - 1 | B51: =INDEX(colBalanceEnd,Completion)
A52: Monthly burn while listed | B52: =ROUND(BalanceAtCompletion*LoanRate/12,2)+ROUND(LandLoan*LandRate/12,2)+ROUND(TaxRate/12*(LandPrice+BuildSpent),2)+ROUND(InsuranceRate/12*EstimateTotal,2)+UtilAfter+StagingMonthly+UpkeepMonthly+HoaMonthly
A53: Max DOM without extension (blank = no loan) | B53: =IF(Commitment=0,"",MAX(0,INT((Maturity-ListMonth)*MonthDays-ClosingDays)))
A55: Checks (each should be 0)
A56: N - period rows | B56: =PeriodCount-RowsInSchedule
A57: Sum of spend - build spent | B57: =SUM(colSpend)-BuildSpent
A58: Sum of equity spend + loan draws - build spent | B58: =SUM(colEquitySpend)+SUM(colLoanDraw)-BuildSpent
A59: Equity return - sum of equity out - profit | B59: =EquityReturn-SUM(colEquityOut)-Profit
A63: Monthly schedule (one row per period k)
A64: Period k | B64: Overlap build start->sale close | C64: Overlap 0->sale close | D64: Overlap build start->completion | E64: Overlap completion->sale close | F64: Overlap list->contract | G64: Draw sine sin(pi(i+0.5)/B) | H64: Hard-cost draw | I64: Spend x | J64: Spend before (S) | K64: Loan drawn before | L64: Equity first | M64: Loan draw (ln) | N64: Equity spend (eq) | O64: Spend through period | P64: Loan drawn through period | Q64: Loan balance at start | R64: Construction points | S64: Draw fee | T64: Construction interest | U64: Interest paid | V64: Interest capitalized | W64: Loan balance at end | X64: Land loan interest | Y64: Extension fees | Z64: Property tax | AA64: Insurance | AB64: Utilities | AC64: Staging | AD64: Upkeep | AE64: HOA | AF64: Land purchase (equity) | AG64: Equity out | AH64: Cumulative equity out | AJ64: Extension j | AK64: Extension j fee period
A65: =0 | B65: =MAX(0,MIN(A65+1,SaleClose)-MAX(A65,BuildStart)) | C65: =MAX(0,MIN(A65+1,SaleClose)-MAX(A65,0)) | D65: =MAX(0,MIN(A65+1,Completion)-MAX(A65,BuildStart)) | E65: =MAX(0,MIN(A65+1,SaleClose)-MAX(A65,Completion)) | F65: =MAX(0,MIN(A65+1,Contract)-MAX(A65,ListMonth)) | G65: =IF(AND(A65>=BuildStart,A65<BuildStart+BuildMonths),SIN(PI()*(A65-BuildStart+0.5)/BuildMonths),0) | H65: =IF(AND(A65>=BuildStart,A65<BuildStart+BuildMonths-1),ROUND(HardActual*(G65/DrawWeightSum),2),IF(A65=BuildStart+BuildMonths-1,HardActual-0,0)) | I65: =IF(A65=0,SoftActual,0)+H65 | J65: =0 | K65: =0 | L65: =MIN(I65,MAX(0,EquityReq-J65)) | M65: =MIN(I65-L65,Commitment-K65) | N65: =L65+(I65-L65-M65) | O65: =J65+I65 | P65: =K65+M65 | Q65: =0 | R65: =IF(AND(A65=BuildStart,Commitment>0),ConstrPoints,0) | S65: =IF(M65>0,DrawFee,0) | T65: =ROUND(Q65*LoanRate/12*B65,2) | U65: =IF(CapFlag=1,0,T65) | V65: =IF(CapFlag=1,T65,0) | W65: =Q65+M65+V65 | X65: =ROUND(LandLoan*LandRate/12*C65,2) | Y65: =COUNTIF(colExtPeriod,A65)*ExtFee | Z65: =ROUND(TaxRate/12*(LandPrice+O65)*C65,2) | AA65: =ROUND(InsuranceRate/12*EstimateTotal*B65,2) | AB65: =ROUND(UtilBuild*D65+UtilAfter*E65,2) | AC65: =ROUND(StagingMonthly*F65,2) | AD65: =ROUND(UpkeepMonthly*E65,2) | AE65: =ROUND(HoaMonthly*C65,2) | AF65: =IF(A65=0,LandPrice-LandLoan+LandClosing+LandPoints,0) | AG65: =AF65+N65+R65+S65+U65+X65+Y65+Z65+AA65+AB65+AC65+AD65+AE65 | AH65: =AG65 | AJ65: =A65 | AK65: =IF(AJ65<ExtCount,INT(Maturity+AJ65*ExtensionMonths),"")
A66: =A65+1 | B66: =MAX(0,MIN(A66+1,SaleClose)-MAX(A66,BuildStart)) | C66: =MAX(0,MIN(A66+1,SaleClose)-MAX(A66,0)) | D66: =MAX(0,MIN(A66+1,Completion)-MAX(A66,BuildStart)) | E66: =MAX(0,MIN(A66+1,SaleClose)-MAX(A66,Completion)) | F66: =MAX(0,MIN(A66+1,Contract)-MAX(A66,ListMonth)) | G66: =IF(AND(A66>=BuildStart,A66<BuildStart+BuildMonths),SIN(PI()*(A66-BuildStart+0.5)/BuildMonths),0) | H66: =IF(AND(A66>=BuildStart,A66<BuildStart+BuildMonths-1),ROUND(HardActual*(G66/DrawWeightSum),2),IF(A66=BuildStart+BuildMonths-1,HardActual-SUM(H$65:H65),0)) | I66: =IF(A66=0,SoftActual,0)+H66 | J66: =O65 | K66: =P65 | L66: =MIN(I66,MAX(0,EquityReq-J66)) | M66: =MIN(I66-L66,Commitment-K66) | N66: =L66+(I66-L66-M66) | O66: =J66+I66 | P66: =K66+M66 | Q66: =W65 | R66: =IF(AND(A66=BuildStart,Commitment>0),ConstrPoints,0) | S66: =IF(M66>0,DrawFee,0) | T66: =ROUND(Q66*LoanRate/12*B66,2) | U66: =IF(CapFlag=1,0,T66) | V66: =IF(CapFlag=1,T66,0) | W66: =Q66+M66+V66 | X66: =ROUND(LandLoan*LandRate/12*C66,2) | Y66: =COUNTIF(colExtPeriod,A66)*ExtFee | Z66: =ROUND(TaxRate/12*(LandPrice+O66)*C66,2) | AA66: =ROUND(InsuranceRate/12*EstimateTotal*B66,2) | AB66: =ROUND(UtilBuild*D66+UtilAfter*E66,2) | AC66: =ROUND(StagingMonthly*F66,2) | AD66: =ROUND(UpkeepMonthly*E66,2) | AE66: =ROUND(HoaMonthly*C66,2) | AF66: =IF(A66=0,LandPrice-LandLoan+LandClosing+LandPoints,0) | AG66: =AF66+N66+R66+S66+U66+X66+Y66+Z66+AA66+AB66+AC66+AD66+AE66 | AH66: =AH65+AG66 | AJ66: =A66 | AK66: =IF(AJ66<ExtCount,INT(Maturity+AJ66*ExtensionMonths),"")
A67: =A66+1 | B67: =MAX(0,MIN(A67+1,SaleClose)-MAX(A67,BuildStart)) | C67: =MAX(0,MIN(A67+1,SaleClose)-MAX(A67,0)) | D67: =MAX(0,MIN(A67+1,Completion)-MAX(A67,BuildStart)) | E67: =MAX(0,MIN(A67+1,SaleClose)-MAX(A67,Completion)) | F67: =MAX(0,MIN(A67+1,Contract)-MAX(A67,ListMonth)) | G67: =IF(AND(A67>=BuildStart,A67<BuildStart+BuildMonths),SIN(PI()*(A67-BuildStart+0.5)/BuildMonths),0) | H67: =IF(AND(A67>=BuildStart,A67<BuildStart+BuildMonths-1),ROUND(HardActual*(G67/DrawWeightSum),2),IF(A67=BuildStart+BuildMonths-1,HardActual-SUM(H$65:H66),0)) | I67: =IF(A67=0,SoftActual,0)+H67 | J67: =O66 | K67: =P66 | L67: =MIN(I67,MAX(0,EquityReq-J67)) | M67: =MIN(I67-L67,Commitment-K67) | N67: =L67+(I67-L67-M67) | O67: =J67+I67 | P67: =K67+M67 | Q67: =W66 | R67: =IF(AND(A67=BuildStart,Commitment>0),ConstrPoints,0) | S67: =IF(M67>0,DrawFee,0) | T67: =ROUND(Q67*LoanRate/12*B67,2) | U67: =IF(CapFlag=1,0,T67) | V67: =IF(CapFlag=1,T67,0) | W67: =Q67+M67+V67 | X67: =ROUND(LandLoan*LandRate/12*C67,2) | Y67: =COUNTIF(colExtPeriod,A67)*ExtFee | Z67: =ROUND(TaxRate/12*(LandPrice+O67)*C67,2) | AA67: =ROUND(InsuranceRate/12*EstimateTotal*B67,2) | AB67: =ROUND(UtilBuild*D67+UtilAfter*E67,2) | AC67: =ROUND(StagingMonthly*F67,2) | AD67: =ROUND(UpkeepMonthly*E67,2) | AE67: =ROUND(HoaMonthly*C67,2) | AF67: =IF(A67=0,LandPrice-LandLoan+LandClosing+LandPoints,0) | AG67: =AF67+N67+R67+S67+U67+X67+Y67+Z67+AA67+AB67+AC67+AD67+AE67 | AH67: =AH66+AG67 | AJ67: =A67 | AK67: =IF(AJ67<ExtCount,INT(Maturity+AJ67*ExtensionMonths),"")
A68: =A67+1 | B68: =MAX(0,MIN(A68+1,SaleClose)-MAX(A68,BuildStart)) | C68: =MAX(0,MIN(A68+1,SaleClose)-MAX(A68,0)) | D68: =MAX(0,MIN(A68+1,Completion)-MAX(A68,BuildStart)) | E68: =MAX(0,MIN(A68+1,SaleClose)-MAX(A68,Completion)) | F68: =MAX(0,MIN(A68+1,Contract)-MAX(A68,ListMonth)) | G68: =IF(AND(A68>=BuildStart,A68<BuildStart+BuildMonths),SIN(PI()*(A68-BuildStart+0.5)/BuildMonths),0) | H68: =IF(AND(A68>=BuildStart,A68<BuildStart+BuildMonths-1),ROUND(HardActual*(G68/DrawWeightSum),2),IF(A68=BuildStart+BuildMonths-1,HardActual-SUM(H$65:H67),0)) | I68: =IF(A68=0,SoftActual,0)+H68 | J68: =O67 | K68: =P67 | L68: =MIN(I68,MAX(0,EquityReq-J68)) | M68: =MIN(I68-L68,Commitment-K68) | N68: =L68+(I68-L68-M68) | O68: =J68+I68 | P68: =K68+M68 | Q68: =W67 | R68: =IF(AND(A68=BuildStart,Commitment>0),ConstrPoints,0) | S68: =IF(M68>0,DrawFee,0) | T68: =ROUND(Q68*LoanRate/12*B68,2) | U68: =IF(CapFlag=1,0,T68) | V68: =IF(CapFlag=1,T68,0) | W68: =Q68+M68+V68 | X68: =ROUND(LandLoan*LandRate/12*C68,2) | Y68: =COUNTIF(colExtPeriod,A68)*ExtFee | Z68: =ROUND(TaxRate/12*(LandPrice+O68)*C68,2) | AA68: =ROUND(InsuranceRate/12*EstimateTotal*B68,2) | AB68: =ROUND(UtilBuild*D68+UtilAfter*E68,2) | AC68: =ROUND(StagingMonthly*F68,2) | AD68: =ROUND(UpkeepMonthly*E68,2) | AE68: =ROUND(HoaMonthly*C68,2) | AF68: =IF(A68=0,LandPrice-LandLoan+LandClosing+LandPoints,0) | AG68: =AF68+N68+R68+S68+U68+X68+Y68+Z68+AA68+AB68+AC68+AD68+AE68 | AH68: =AH67+AG68 | AJ68: =A68 | AK68: =IF(AJ68<ExtCount,INT(Maturity+AJ68*ExtensionMonths),"")
A69: =A68+1 | B69: =MAX(0,MIN(A69+1,SaleClose)-MAX(A69,BuildStart)) | C69: =MAX(0,MIN(A69+1,SaleClose)-MAX(A69,0)) | D69: =MAX(0,MIN(A69+1,Completion)-MAX(A69,BuildStart)) | E69: =MAX(0,MIN(A69+1,SaleClose)-MAX(A69,Completion)) | F69: =MAX(0,MIN(A69+1,Contract)-MAX(A69,ListMonth)) | G69: =IF(AND(A69>=BuildStart,A69<BuildStart+BuildMonths),SIN(PI()*(A69-BuildStart+0.5)/BuildMonths),0) | H69: =IF(AND(A69>=BuildStart,A69<BuildStart+BuildMonths-1),ROUND(HardActual*(G69/DrawWeightSum),2),IF(A69=BuildStart+BuildMonths-1,HardActual-SUM(H$65:H68),0)) | I69: =IF(A69=0,SoftActual,0)+H69 | J69: =O68 | K69: =P68 | L69: =MIN(I69,MAX(0,EquityReq-J69)) | M69: =MIN(I69-L69,Commitment-K69) | N69: =L69+(I69-L69-M69) | O69: =J69+I69 | P69: =K69+M69 | Q69: =W68 | R69: =IF(AND(A69=BuildStart,Commitment>0),ConstrPoints,0) | S69: =IF(M69>0,DrawFee,0) | T69: =ROUND(Q69*LoanRate/12*B69,2) | U69: =IF(CapFlag=1,0,T69) | V69: =IF(CapFlag=1,T69,0) | W69: =Q69+M69+V69 | X69: =ROUND(LandLoan*LandRate/12*C69,2) | Y69: =COUNTIF(colExtPeriod,A69)*ExtFee | Z69: =ROUND(TaxRate/12*(LandPrice+O69)*C69,2) | AA69: =ROUND(InsuranceRate/12*EstimateTotal*B69,2) | AB69: =ROUND(UtilBuild*D69+UtilAfter*E69,2) | AC69: =ROUND(StagingMonthly*F69,2) | AD69: =ROUND(UpkeepMonthly*E69,2) | AE69: =ROUND(HoaMonthly*C69,2) | AF69: =IF(A69=0,LandPrice-LandLoan+LandClosing+LandPoints,0) | AG69: =AF69+N69+R69+S69+U69+X69+Y69+Z69+AA69+AB69+AC69+AD69+AE69 | AH69: =AH68+AG69 | AJ69: =A69 | AK69: =IF(AJ69<ExtCount,INT(Maturity+AJ69*ExtensionMonths),"")
A70: =A69+1 | B70: =MAX(0,MIN(A70+1,SaleClose)-MAX(A70,BuildStart)) | C70: =MAX(0,MIN(A70+1,SaleClose)-MAX(A70,0)) | D70: =MAX(0,MIN(A70+1,Completion)-MAX(A70,BuildStart)) | E70: =MAX(0,MIN(A70+1,SaleClose)-MAX(A70,Completion)) | F70: =MAX(0,MIN(A70+1,Contract)-MAX(A70,ListMonth)) | G70: =IF(AND(A70>=BuildStart,A70<BuildStart+BuildMonths),SIN(PI()*(A70-BuildStart+0.5)/BuildMonths),0) | H70: =IF(AND(A70>=BuildStart,A70<BuildStart+BuildMonths-1),ROUND(HardActual*(G70/DrawWeightSum),2),IF(A70=BuildStart+BuildMonths-1,HardActual-SUM(H$65:H69),0)) | I70: =IF(A70=0,SoftActual,0)+H70 | J70: =O69 | K70: =P69 | L70: =MIN(I70,MAX(0,EquityReq-J70)) | M70: =MIN(I70-L70,Commitment-K70) | N70: =L70+(I70-L70-M70) | O70: =J70+I70 | P70: =K70+M70 | Q70: =W69 | R70: =IF(AND(A70=BuildStart,Commitment>0),ConstrPoints,0) | S70: =IF(M70>0,DrawFee,0) | T70: =ROUND(Q70*LoanRate/12*B70,2) | U70: =IF(CapFlag=1,0,T70) | V70: =IF(CapFlag=1,T70,0) | W70: =Q70+M70+V70 | X70: =ROUND(LandLoan*LandRate/12*C70,2) | Y70: =COUNTIF(colExtPeriod,A70)*ExtFee | Z70: =ROUND(TaxRate/12*(LandPrice+O70)*C70,2) | AA70: =ROUND(InsuranceRate/12*EstimateTotal*B70,2) | AB70: =ROUND(UtilBuild*D70+UtilAfter*E70,2) | AC70: =ROUND(StagingMonthly*F70,2) | AD70: =ROUND(UpkeepMonthly*E70,2) | AE70: =ROUND(HoaMonthly*C70,2) | AF70: =IF(A70=0,LandPrice-LandLoan+LandClosing+LandPoints,0) | AG70: =AF70+N70+R70+S70+U70+X70+Y70+Z70+AA70+AB70+AC70+AD70+AE70 | AH70: =AH69+AG70 | AJ70: =A70 | AK70: =IF(AJ70<ExtCount,INT(Maturity+AJ70*ExtensionMonths),"")
A71: =A70+1 | B71: =MAX(0,MIN(A71+1,SaleClose)-MAX(A71,BuildStart)) | C71: =MAX(0,MIN(A71+1,SaleClose)-MAX(A71,0)) | D71: =MAX(0,MIN(A71+1,Completion)-MAX(A71,BuildStart)) | E71: =MAX(0,MIN(A71+1,SaleClose)-MAX(A71,Completion)) | F71: =MAX(0,MIN(A71+1,Contract)-MAX(A71,ListMonth)) | G71: =IF(AND(A71>=BuildStart,A71<BuildStart+BuildMonths),SIN(PI()*(A71-BuildStart+0.5)/BuildMonths),0) | H71: =IF(AND(A71>=BuildStart,A71<BuildStart+BuildMonths-1),ROUND(HardActual*(G71/DrawWeightSum),2),IF(A71=BuildStart+BuildMonths-1,HardActual-SUM(H$65:H70),0)) | I71: =IF(A71=0,SoftActual,0)+H71 | J71: =O70 | K71: =P70 | L71: =MIN(I71,MAX(0,EquityReq-J71)) | M71: =MIN(I71-L71,Commitment-K71) | N71: =L71+(I71-L71-M71) | O71: =J71+I71 | P71: =K71+M71 | Q71: =W70 | R71: =IF(AND(A71=BuildStart,Commitment>0),ConstrPoints,0) | S71: =IF(M71>0,DrawFee,0) | T71: =ROUND(Q71*LoanRate/12*B71,2) | U71: =IF(CapFlag=1,0,T71) | V71: =IF(CapFlag=1,T71,0) | W71: =Q71+M71+V71 | X71: =ROUND(LandLoan*LandRate/12*C71,2) | Y71: =COUNTIF(colExtPeriod,A71)*ExtFee | Z71: =ROUND(TaxRate/12*(LandPrice+O71)*C71,2) | AA71: =ROUND(InsuranceRate/12*EstimateTotal*B71,2) | AB71: =ROUND(UtilBuild*D71+UtilAfter*E71,2) | AC71: =ROUND(StagingMonthly*F71,2) | AD71: =ROUND(UpkeepMonthly*E71,2) | AE71: =ROUND(HoaMonthly*C71,2) | AF71: =IF(A71=0,LandPrice-LandLoan+LandClosing+LandPoints,0) | AG71: =AF71+N71+R71+S71+U71+X71+Y71+Z71+AA71+AB71+AC71+AD71+AE71 | AH71: =AH70+AG71 | AJ71: =A71 | AK71: =IF(AJ71<ExtCount,INT(Maturity+AJ71*ExtensionMonths),"")
A72: =A71+1 | B72: =MAX(0,MIN(A72+1,SaleClose)-MAX(A72,BuildStart)) | C72: =MAX(0,MIN(A72+1,SaleClose)-MAX(A72,0)) | D72: =MAX(0,MIN(A72+1,Completion)-MAX(A72,BuildStart)) | E72: =MAX(0,MIN(A72+1,SaleClose)-MAX(A72,Completion)) | F72: =MAX(0,MIN(A72+1,Contract)-MAX(A72,ListMonth)) | G72: =IF(AND(A72>=BuildStart,A72<BuildStart+BuildMonths),SIN(PI()*(A72-BuildStart+0.5)/BuildMonths),0) | H72: =IF(AND(A72>=BuildStart,A72<BuildStart+BuildMonths-1),ROUND(HardActual*(G72/DrawWeightSum),2),IF(A72=BuildStart+BuildMonths-1,HardActual-SUM(H$65:H71),0)) | I72: =IF(A72=0,SoftActual,0)+H72 | J72: =O71 | K72: =P71 | L72: =MIN(I72,MAX(0,EquityReq-J72)) | M72: =MIN(I72-L72,Commitment-K72) | N72: =L72+(I72-L72-M72) | O72: =J72+I72 | P72: =K72+M72 | Q72: =W71 | R72: =IF(AND(A72=BuildStart,Commitment>0),ConstrPoints,0) | S72: =IF(M72>0,DrawFee,0) | T72: =ROUND(Q72*LoanRate/12*B72,2) | U72: =IF(CapFlag=1,0,T72) | V72: =IF(CapFlag=1,T72,0) | W72: =Q72+M72+V72 | X72: =ROUND(LandLoan*LandRate/12*C72,2) | Y72: =COUNTIF(colExtPeriod,A72)*ExtFee | Z72: =ROUND(TaxRate/12*(LandPrice+O72)*C72,2) | AA72: =ROUND(InsuranceRate/12*EstimateTotal*B72,2) | AB72: =ROUND(UtilBuild*D72+UtilAfter*E72,2) | AC72: =ROUND(StagingMonthly*F72,2) | AD72: =ROUND(UpkeepMonthly*E72,2) | AE72: =ROUND(HoaMonthly*C72,2) | AF72: =IF(A72=0,LandPrice-LandLoan+LandClosing+LandPoints,0) | AG72: =AF72+N72+R72+S72+U72+X72+Y72+Z72+AA72+AB72+AC72+AD72+AE72 | AH72: =AH71+AG72 | AJ72: =A72 | AK72: =IF(AJ72<ExtCount,INT(Maturity+AJ72*ExtensionMonths),"")
A73: =A72+1 | B73: =MAX(0,MIN(A73+1,SaleClose)-MAX(A73,BuildStart)) | C73: =MAX(0,MIN(A73+1,SaleClose)-MAX(A73,0)) | D73: =MAX(0,MIN(A73+1,Completion)-MAX(A73,BuildStart)) | E73: =MAX(0,MIN(A73+1,SaleClose)-MAX(A73,Completion)) | F73: =MAX(0,MIN(A73+1,Contract)-MAX(A73,ListMonth)) | G73: =IF(AND(A73>=BuildStart,A73<BuildStart+BuildMonths),SIN(PI()*(A73-BuildStart+0.5)/BuildMonths),0) | H73: =IF(AND(A73>=BuildStart,A73<BuildStart+BuildMonths-1),ROUND(HardActual*(G73/DrawWeightSum),2),IF(A73=BuildStart+BuildMonths-1,HardActual-SUM(H$65:H72),0)) | I73: =IF(A73=0,SoftActual,0)+H73 | J73: =O72 | K73: =P72 | L73: =MIN(I73,MAX(0,EquityReq-J73)) | M73: =MIN(I73-L73,Commitment-K73) | N73: =L73+(I73-L73-M73) | O73: =J73+I73 | P73: =K73+M73 | Q73: =W72 | R73: =IF(AND(A73=BuildStart,Commitment>0),ConstrPoints,0) | S73: =IF(M73>0,DrawFee,0) | T73: =ROUND(Q73*LoanRate/12*B73,2) | U73: =IF(CapFlag=1,0,T73) | V73: =IF(CapFlag=1,T73,0) | W73: =Q73+M73+V73 | X73: =ROUND(LandLoan*LandRate/12*C73,2) | Y73: =COUNTIF(colExtPeriod,A73)*ExtFee | Z73: =ROUND(TaxRate/12*(LandPrice+O73)*C73,2) | AA73: =ROUND(InsuranceRate/12*EstimateTotal*B73,2) | AB73: =ROUND(UtilBuild*D73+UtilAfter*E73,2) | AC73: =ROUND(StagingMonthly*F73,2) | AD73: =ROUND(UpkeepMonthly*E73,2) | AE73: =ROUND(HoaMonthly*C73,2) | AF73: =IF(A73=0,LandPrice-LandLoan+LandClosing+LandPoints,0) | AG73: =AF73+N73+R73+S73+U73+X73+Y73+Z73+AA73+AB73+AC73+AD73+AE73 | AH73: =AH72+AG73 | AJ73: =A73 | AK73: =IF(AJ73<ExtCount,INT(Maturity+AJ73*ExtensionMonths),"")
A74: =A73+1 | B74: =MAX(0,MIN(A74+1,SaleClose)-MAX(A74,BuildStart)) | C74: =MAX(0,MIN(A74+1,SaleClose)-MAX(A74,0)) | D74: =MAX(0,MIN(A74+1,Completion)-MAX(A74,BuildStart)) | E74: =MAX(0,MIN(A74+1,SaleClose)-MAX(A74,Completion)) | F74: =MAX(0,MIN(A74+1,Contract)-MAX(A74,ListMonth)) | G74: =IF(AND(A74>=BuildStart,A74<BuildStart+BuildMonths),SIN(PI()*(A74-BuildStart+0.5)/BuildMonths),0) | H74: =IF(AND(A74>=BuildStart,A74<BuildStart+BuildMonths-1),ROUND(HardActual*(G74/DrawWeightSum),2),IF(A74=BuildStart+BuildMonths-1,HardActual-SUM(H$65:H73),0)) | I74: =IF(A74=0,SoftActual,0)+H74 | J74: =O73 | K74: =P73 | L74: =MIN(I74,MAX(0,EquityReq-J74)) | M74: =MIN(I74-L74,Commitment-K74) | N74: =L74+(I74-L74-M74) | O74: =J74+I74 | P74: =K74+M74 | Q74: =W73 | R74: =IF(AND(A74=BuildStart,Commitment>0),ConstrPoints,0) | S74: =IF(M74>0,DrawFee,0) | T74: =ROUND(Q74*LoanRate/12*B74,2) | U74: =IF(CapFlag=1,0,T74) | V74: =IF(CapFlag=1,T74,0) | W74: =Q74+M74+V74 | X74: =ROUND(LandLoan*LandRate/12*C74,2) | Y74: =COUNTIF(colExtPeriod,A74)*ExtFee | Z74: =ROUND(TaxRate/12*(LandPrice+O74)*C74,2) | AA74: =ROUND(InsuranceRate/12*EstimateTotal*B74,2) | AB74: =ROUND(UtilBuild*D74+UtilAfter*E74,2) | AC74: =ROUND(StagingMonthly*F74,2) | AD74: =ROUND(UpkeepMonthly*E74,2) | AE74: =ROUND(HoaMonthly*C74,2) | AF74: =IF(A74=0,LandPrice-LandLoan+LandClosing+LandPoints,0) | AG74: =AF74+N74+R74+S74+U74+X74+Y74+Z74+AA74+AB74+AC74+AD74+AE74 | AH74: =AH73+AG74 | AJ74: =A74 | AK74: =IF(AJ74<ExtCount,INT(Maturity+AJ74*ExtensionMonths),"")
A75: =A74+1 | B75: =MAX(0,MIN(A75+1,SaleClose)-MAX(A75,BuildStart)) | C75: =MAX(0,MIN(A75+1,SaleClose)-MAX(A75,0)) | D75: =MAX(0,MIN(A75+1,Completion)-MAX(A75,BuildStart)) | E75: =MAX(0,MIN(A75+1,SaleClose)-MAX(A75,Completion)) | F75: =MAX(0,MIN(A75+1,Contract)-MAX(A75,ListMonth)) | G75: =IF(AND(A75>=BuildStart,A75<BuildStart+BuildMonths),SIN(PI()*(A75-BuildStart+0.5)/BuildMonths),0) | H75: =IF(AND(A75>=BuildStart,A75<BuildStart+BuildMonths-1),ROUND(HardActual*(G75/DrawWeightSum),2),IF(A75=BuildStart+BuildMonths-1,HardActual-SUM(H$65:H74),0)) | I75: =IF(A75=0,SoftActual,0)+H75 | J75: =O74 | K75: =P74 | L75: =MIN(I75,MAX(0,EquityReq-J75)) | M75: =MIN(I75-L75,Commitment-K75) | N75: =L75+(I75-L75-M75) | O75: =J75+I75 | P75: =K75+M75 | Q75: =W74 | R75: =IF(AND(A75=BuildStart,Commitment>0),ConstrPoints,0) | S75: =IF(M75>0,DrawFee,0) | T75: =ROUND(Q75*LoanRate/12*B75,2) | U75: =IF(CapFlag=1,0,T75) | V75: =IF(CapFlag=1,T75,0) | W75: =Q75+M75+V75 | X75: =ROUND(LandLoan*LandRate/12*C75,2) | Y75: =COUNTIF(colExtPeriod,A75)*ExtFee | Z75: =ROUND(TaxRate/12*(LandPrice+O75)*C75,2) | AA75: =ROUND(InsuranceRate/12*EstimateTotal*B75,2) | AB75: =ROUND(UtilBuild*D75+UtilAfter*E75,2) | AC75: =ROUND(StagingMonthly*F75,2) | AD75: =ROUND(UpkeepMonthly*E75,2) | AE75: =ROUND(HoaMonthly*C75,2) | AF75: =IF(A75=0,LandPrice-LandLoan+LandClosing+LandPoints,0) | AG75: =AF75+N75+R75+S75+U75+X75+Y75+Z75+AA75+AB75+AC75+AD75+AE75 | AH75: =AH74+AG75 | AJ75: =A75 | AK75: =IF(AJ75<ExtCount,INT(Maturity+AJ75*ExtensionMonths),"")
A76: =A75+1 | B76: =MAX(0,MIN(A76+1,SaleClose)-MAX(A76,BuildStart)) | C76: =MAX(0,MIN(A76+1,SaleClose)-MAX(A76,0)) | D76: =MAX(0,MIN(A76+1,Completion)-MAX(A76,BuildStart)) | E76: =MAX(0,MIN(A76+1,SaleClose)-MAX(A76,Completion)) | F76: =MAX(0,MIN(A76+1,Contract)-MAX(A76,ListMonth)) | G76: =IF(AND(A76>=BuildStart,A76<BuildStart+BuildMonths),SIN(PI()*(A76-BuildStart+0.5)/BuildMonths),0) | H76: =IF(AND(A76>=BuildStart,A76<BuildStart+BuildMonths-1),ROUND(HardActual*(G76/DrawWeightSum),2),IF(A76=BuildStart+BuildMonths-1,HardActual-SUM(H$65:H75),0)) | I76: =IF(A76=0,SoftActual,0)+H76 | J76: =O75 | K76: =P75 | L76: =MIN(I76,MAX(0,EquityReq-J76)) | M76: =MIN(I76-L76,Commitment-K76) | N76: =L76+(I76-L76-M76) | O76: =J76+I76 | P76: =K76+M76 | Q76: =W75 | R76: =IF(AND(A76=BuildStart,Commitment>0),ConstrPoints,0) | S76: =IF(M76>0,DrawFee,0) | T76: =ROUND(Q76*LoanRate/12*B76,2) | U76: =IF(CapFlag=1,0,T76) | V76: =IF(CapFlag=1,T76,0) | W76: =Q76+M76+V76 | X76: =ROUND(LandLoan*LandRate/12*C76,2) | Y76: =COUNTIF(colExtPeriod,A76)*ExtFee | Z76: =ROUND(TaxRate/12*(LandPrice+O76)*C76,2) | AA76: =ROUND(InsuranceRate/12*EstimateTotal*B76,2) | AB76: =ROUND(UtilBuild*D76+UtilAfter*E76,2) | AC76: =ROUND(StagingMonthly*F76,2) | AD76: =ROUND(UpkeepMonthly*E76,2) | AE76: =ROUND(HoaMonthly*C76,2) | AF76: =IF(A76=0,LandPrice-LandLoan+LandClosing+LandPoints,0) | AG76: =AF76+N76+R76+S76+U76+X76+Y76+Z76+AA76+AB76+AC76+AD76+AE76 | AH76: =AH75+AG76 | AJ76: =A76 | AK76: =IF(AJ76<ExtCount,INT(Maturity+AJ76*ExtensionMonths),"")
A77: =A76+1 | B77: =MAX(0,MIN(A77+1,SaleClose)-MAX(A77,BuildStart)) | C77: =MAX(0,MIN(A77+1,SaleClose)-MAX(A77,0)) | D77: =MAX(0,MIN(A77+1,Completion)-MAX(A77,BuildStart)) | E77: =MAX(0,MIN(A77+1,SaleClose)-MAX(A77,Completion)) | F77: =MAX(0,MIN(A77+1,Contract)-MAX(A77,ListMonth)) | G77: =IF(AND(A77>=BuildStart,A77<BuildStart+BuildMonths),SIN(PI()*(A77-BuildStart+0.5)/BuildMonths),0) | H77: =IF(AND(A77>=BuildStart,A77<BuildStart+BuildMonths-1),ROUND(HardActual*(G77/DrawWeightSum),2),IF(A77=BuildStart+BuildMonths-1,HardActual-SUM(H$65:H76),0)) | I77: =IF(A77=0,SoftActual,0)+H77 | J77: =O76 | K77: =P76 | L77: =MIN(I77,MAX(0,EquityReq-J77)) | M77: =MIN(I77-L77,Commitment-K77) | N77: =L77+(I77-L77-M77) | O77: =J77+I77 | P77: =K77+M77 | Q77: =W76 | R77: =IF(AND(A77=BuildStart,Commitment>0),ConstrPoints,0) | S77: =IF(M77>0,DrawFee,0) | T77: =ROUND(Q77*LoanRate/12*B77,2) | U77: =IF(CapFlag=1,0,T77) | V77: =IF(CapFlag=1,T77,0) | W77: =Q77+M77+V77 | X77: =ROUND(LandLoan*LandRate/12*C77,2) | Y77: =COUNTIF(colExtPeriod,A77)*ExtFee | Z77: =ROUND(TaxRate/12*(LandPrice+O77)*C77,2) | AA77: =ROUND(InsuranceRate/12*EstimateTotal*B77,2) | AB77: =ROUND(UtilBuild*D77+UtilAfter*E77,2) | AC77: =ROUND(StagingMonthly*F77,2) | AD77: =ROUND(UpkeepMonthly*E77,2) | AE77: =ROUND(HoaMonthly*C77,2) | AF77: =IF(A77=0,LandPrice-LandLoan+LandClosing+LandPoints,0) | AG77: =AF77+N77+R77+S77+U77+X77+Y77+Z77+AA77+AB77+AC77+AD77+AE77 | AH77: =AH76+AG77 | AJ77: =A77 | AK77: =IF(AJ77<ExtCount,INT(Maturity+AJ77*ExtensionMonths),"")
... A79: =A78+1 | B79: =MAX(0,MIN(A79+1,SaleClose)-MAX(A79,BuildStart)) | C79: =MAX(0,MIN(A79+1,SaleClose)-MAX(A79,0)) | D79: =MAX(0,MIN(A79+1,Completion)-MAX(A79,BuildStart)) | E79: =MAX(0,MIN(A79+1,SaleClose)-MAX(A79,Completion)) | F79: =MAX(0,MIN(A79+1,Contract)-MAX(A79,ListMonth)) | G79: =IF(AND(A79>=BuildStart,A79<BuildStart+BuildMonths),SIN(PI()*(A79-BuildStart+0.5)/BuildMonths),0) | H79: =IF(AND(A79>=BuildStart,A79<BuildStart+BuildMonths-1),ROUND(HardActual*(G79/DrawWeightSum),2),IF(A79=BuildStart+BuildMonths-1,HardActual-SUM(H$65:H78),0)) | I79: =IF(A79=0,SoftActual,0)+H79 | J79: =O78 | K79: =P78 | L79: =MIN(I79,MAX(0,EquityReq-J79)) | M79: =MIN(I79-L79,Commitment-K79) | N79: =L79+(I79-L79-M79) | O79: =J79+I79 | P79: =K79+M79 | Q79: =W78 | R79: =IF(AND(A79=BuildStart,Commitment>0),ConstrPoints,0) | S79: =IF(M79>0,DrawFee,0) | T79: =ROUND(Q79*LoanRate/12*B79,2) | U79: =IF(CapFlag=1,0,T79) | V79: =IF(CapFlag=1,T79,0) | W79: =Q79+M79+V79 | X79: =ROUND(LandLoan*LandRate/12*C79,2) | Y79: =COUNTIF(colExtPeriod,A79)*ExtFee | Z79: =ROUND(TaxRate/12*(LandPrice+O79)*C79,2) | AA79: =ROUND(InsuranceRate/12*EstimateTotal*B79,2) | AB79: =ROUND(UtilBuild*D79+UtilAfter*E79,2) | AC79: =ROUND(StagingMonthly*F79,2) | AD79: =ROUND(UpkeepMonthly*E79,2) | AE79: =ROUND(HoaMonthly*C79,2) | AF79: =IF(A79=0,LandPrice-LandLoan+LandClosing+LandPoints,0) | AG79: =AF79+N79+R79+S79+U79+X79+Y79+Z79+AA79+AB79+AC79+AD79+AE79 | AH79: =AH78+AG79 | AJ79: =A79 | AK79: =IF(AJ79<ExtCount,INT(Maturity+AJ79*ExtensionMonths),"")

Sheet stress
A1: Golden deal - stress scenario
A2: Every value below is a formula implementing the Reference cash-flow algorithm (dollars).
A4: Scenario inputs
A5: Sale price | B5: =Inputs!$B$47
A6: Days on market | B6: =Inputs!$C$47
A7: Cost overrun | B7: =Inputs!$D$47
A9: Times (months) - Reference step 1
A10: Build start = P | B10: =PreConMonths
A11: Completion = P + B | B11: =BuildStart+BuildMonths
A12: List = completion - L | B12: =Completion-ListEarlyMonths
A13: Contract = list + DOM / MONTH_DAYS | B13: =ListMonth+DomDays/MonthDays
A14: Sale close = max(contract + closingDays / MONTH_DAYS, completion) | B14: =MAX(Contract+ClosingDays/MonthDays,Completion)
A15: Loan maturity = build start + term | B15: =BuildStart+TermMonths
A16: Periods N = ceil(sale close) | B16: =CEILING(SaleClose,1)
A17: Period rows in this sheet | B17: =COUNT(colK)
A19: Costs and loan - Reference steps 2-8
A20: Soft actual = round(soft x (1 + overrun)) | B20: =ROUND(SoftCost*(1+Overrun),2)
A21: Hard actual = round(hard x (1 + overrun)) | B21: =ROUND(HardCost*(1+Overrun),2)
A22: Sum of draw sines | B22: =SUM(colSine)
A23: Loan commitment = round(LTC x estimate total) | B23: =ROUND(Ltc*EstimateTotal,2)
A24: Equity requirement = estimate total - commitment | B24: =EstimateTotal-Commitment
A25: Construction points = round(points x commitment) | B25: =IF(Commitment>0,ROUND(PointsPct*Commitment,2),0)
A26: Land loan = round(LTV x land price) | B26: =ROUND(LandLtv*LandPrice,2)
A27: Land points = round(points x land loan) | B27: =ROUND(LandPointsPct*LandLoan,2)
A28: Extensions n | B28: =IF(AND(Commitment>0,SaleClose>Maturity),CEILING((SaleClose-Maturity)/ExtensionMonths,1),0)
A29: Extension fee each = round(extension % x commitment) | B29: =ROUND(ExtensionPct*Commitment,2)
A30: Interest capitalized (1 = yes) | B30: =IF(InterestMode="capitalized",1,0)
A32: Sale (at sale close, booked on period N-1) - Reference step 11
A33: Commissions = round(price x (listing + buyer)) | B33: =ROUND(SalePrice*(ListingPct+BuyerPct),2)
A34: Closing = round(price x closing %) | B34: =ROUND(SalePrice*ClosingPct,2)
A35: Concessions | B35: =Concessions
A36: Net = price - commissions - closing - concessions | B36: =SalePrice-Commissions-SaleClosing-SaleConcessions
A37: Loan drawn | B37: =SUM(colLoanDraw)
A38: Capitalized interest | B38: =SUM(colInterestCap)
A39: Loan payoff = drawn + capitalized interest + land loan | B39: =LoanDrawn+CapInterest+LandLoan
A40: Equity return = net - payoff | B40: =NetProceeds-Payoff
A42: Totals and metrics - Reference steps 12-15
A43: Build spent = soft actual + hard actual | B43: =SoftActual+HardActual
A44: Financing | B44: =SUM(colPoints)+LandPoints+SUM(colInterest)+SUM(colLandInterest)+SUM(colDrawFee)+SUM(colExtensionFee)
A45: Carry | B45: =SUM(colTax)+SUM(colInsurance)+SUM(colUtilities)+SUM(colStaging)+SUM(colUpkeep)+SUM(colHoa)
A46: Total project cost | B46: =LandPrice+LandClosing+BuildSpent+Financing+Carry
A47: Selling costs | B47: =Commissions+SaleClosing+SaleConcessions
A48: Profit | B48: =SalePrice-SellingCosts-TotalProjectCost
A49: Peak cash | B49: =MAX(colCumEquity)
A50: Break-even sale price | B50: =ROUND((TotalProjectCost+Concessions)/(1-ListingPct-BuyerPct-ClosingPct),2)
A51: Loan balance after period completion - 1 | B51: =INDEX(colBalanceEnd,Completion)
A52: Monthly burn while listed | B52: =ROUND(BalanceAtCompletion*LoanRate/12,2)+ROUND(LandLoan*LandRate/12,2)+ROUND(TaxRate/12*(LandPrice+BuildSpent),2)+ROUND(InsuranceRate/12*EstimateTotal,2)+UtilAfter+StagingMonthly+UpkeepMonthly+HoaMonthly
A53: Max DOM without extension (blank = no loan) | B53: =IF(Commitment=0,"",MAX(0,INT((Maturity-ListMonth)*MonthDays-ClosingDays)))
A55: Checks (each should be 0)
A56: N - period rows | B56: =PeriodCount-RowsInSchedule
A57: Sum of spend - build spent | B57: =SUM(colSpend)-BuildSpent
A58: Sum of equity spend + loan draws - build spent | B58: =SUM(colEquitySpend)+SUM(colLoanDraw)-BuildSpent
A59: Equity return - sum of equity out - profit | B59: =EquityReturn-SUM(colEquityOut)-Profit
A63: Monthly schedule (one row per period k)
A64: Period k | B64: Overlap build start->sale close | C64: Overlap 0->sale close | D64: Overlap build start->completion | E64: Overlap completion->sale close | F64: Overlap list->contract | G64: Draw sine sin(pi(i+0.5)/B) | H64: Hard-cost draw | I64: Spend x | J64: Spend before (S) | K64: Loan drawn before | L64: Equity first | M64: Loan draw (ln) | N64: Equity spend (eq) | O64: Spend through period | P64: Loan drawn through period | Q64: Loan balance at start | R64: Construction points | S64: Draw fee | T64: Construction interest | U64: Interest paid | V64: Interest capitalized | W64: Loan balance at end | X64: Land loan interest | Y64: Extension fees | Z64: Property tax | AA64: Insurance | AB64: Utilities | AC64: Staging | AD64: Upkeep | AE64: HOA | AF64: Land purchase (equity) | AG64: Equity out | AH64: Cumulative equity out | AJ64: Extension j | AK64: Extension j fee period
A65: =0 | B65: =MAX(0,MIN(A65+1,SaleClose)-MAX(A65,BuildStart)) | C65: =MAX(0,MIN(A65+1,SaleClose)-MAX(A65,0)) | D65: =MAX(0,MIN(A65+1,Completion)-MAX(A65,BuildStart)) | E65: =MAX(0,MIN(A65+1,SaleClose)-MAX(A65,Completion)) | F65: =MAX(0,MIN(A65+1,Contract)-MAX(A65,ListMonth)) | G65: =IF(AND(A65>=BuildStart,A65<BuildStart+BuildMonths),SIN(PI()*(A65-BuildStart+0.5)/BuildMonths),0) | H65: =IF(AND(A65>=BuildStart,A65<BuildStart+BuildMonths-1),ROUND(HardActual*(G65/DrawWeightSum),2),IF(A65=BuildStart+BuildMonths-1,HardActual-0,0)) | I65: =IF(A65=0,SoftActual,0)+H65 | J65: =0 | K65: =0 | L65: =MIN(I65,MAX(0,EquityReq-J65)) | M65: =MIN(I65-L65,Commitment-K65) | N65: =L65+(I65-L65-M65) | O65: =J65+I65 | P65: =K65+M65 | Q65: =0 | R65: =IF(AND(A65=BuildStart,Commitment>0),ConstrPoints,0) | S65: =IF(M65>0,DrawFee,0) | T65: =ROUND(Q65*LoanRate/12*B65,2) | U65: =IF(CapFlag=1,0,T65) | V65: =IF(CapFlag=1,T65,0) | W65: =Q65+M65+V65 | X65: =ROUND(LandLoan*LandRate/12*C65,2) | Y65: =COUNTIF(colExtPeriod,A65)*ExtFee | Z65: =ROUND(TaxRate/12*(LandPrice+O65)*C65,2) | AA65: =ROUND(InsuranceRate/12*EstimateTotal*B65,2) | AB65: =ROUND(UtilBuild*D65+UtilAfter*E65,2) | AC65: =ROUND(StagingMonthly*F65,2) | AD65: =ROUND(UpkeepMonthly*E65,2) | AE65: =ROUND(HoaMonthly*C65,2) | AF65: =IF(A65=0,LandPrice-LandLoan+LandClosing+LandPoints,0) | AG65: =AF65+N65+R65+S65+U65+X65+Y65+Z65+AA65+AB65+AC65+AD65+AE65 | AH65: =AG65 | AJ65: =A65 | AK65: =IF(AJ65<ExtCount,INT(Maturity+AJ65*ExtensionMonths),"")
A66: =A65+1 | B66: =MAX(0,MIN(A66+1,SaleClose)-MAX(A66,BuildStart)) | C66: =MAX(0,MIN(A66+1,SaleClose)-MAX(A66,0)) | D66: =MAX(0,MIN(A66+1,Completion)-MAX(A66,BuildStart)) | E66: =MAX(0,MIN(A66+1,SaleClose)-MAX(A66,Completion)) | F66: =MAX(0,MIN(A66+1,Contract)-MAX(A66,ListMonth)) | G66: =IF(AND(A66>=BuildStart,A66<BuildStart+BuildMonths),SIN(PI()*(A66-BuildStart+0.5)/BuildMonths),0) | H66: =IF(AND(A66>=BuildStart,A66<BuildStart+BuildMonths-1),ROUND(HardActual*(G66/DrawWeightSum),2),IF(A66=BuildStart+BuildMonths-1,HardActual-SUM(H$65:H65),0)) | I66: =IF(A66=0,SoftActual,0)+H66 | J66: =O65 | K66: =P65 | L66: =MIN(I66,MAX(0,EquityReq-J66)) | M66: =MIN(I66-L66,Commitment-K66) | N66: =L66+(I66-L66-M66) | O66: =J66+I66 | P66: =K66+M66 | Q66: =W65 | R66: =IF(AND(A66=BuildStart,Commitment>0),ConstrPoints,0) | S66: =IF(M66>0,DrawFee,0) | T66: =ROUND(Q66*LoanRate/12*B66,2) | U66: =IF(CapFlag=1,0,T66) | V66: =IF(CapFlag=1,T66,0) | W66: =Q66+M66+V66 | X66: =ROUND(LandLoan*LandRate/12*C66,2) | Y66: =COUNTIF(colExtPeriod,A66)*ExtFee | Z66: =ROUND(TaxRate/12*(LandPrice+O66)*C66,2) | AA66: =ROUND(InsuranceRate/12*EstimateTotal*B66,2) | AB66: =ROUND(UtilBuild*D66+UtilAfter*E66,2) | AC66: =ROUND(StagingMonthly*F66,2) | AD66: =ROUND(UpkeepMonthly*E66,2) | AE66: =ROUND(HoaMonthly*C66,2) | AF66: =IF(A66=0,LandPrice-LandLoan+LandClosing+LandPoints,0) | AG66: =AF66+N66+R66+S66+U66+X66+Y66+Z66+AA66+AB66+AC66+AD66+AE66 | AH66: =AH65+AG66 | AJ66: =A66 | AK66: =IF(AJ66<ExtCount,INT(Maturity+AJ66*ExtensionMonths),"")
A67: =A66+1 | B67: =MAX(0,MIN(A67+1,SaleClose)-MAX(A67,BuildStart)) | C67: =MAX(0,MIN(A67+1,SaleClose)-MAX(A67,0)) | D67: =MAX(0,MIN(A67+1,Completion)-MAX(A67,BuildStart)) | E67: =MAX(0,MIN(A67+1,SaleClose)-MAX(A67,Completion)) | F67: =MAX(0,MIN(A67+1,Contract)-MAX(A67,ListMonth)) | G67: =IF(AND(A67>=BuildStart,A67<BuildStart+BuildMonths),SIN(PI()*(A67-BuildStart+0.5)/BuildMonths),0) | H67: =IF(AND(A67>=BuildStart,A67<BuildStart+BuildMonths-1),ROUND(HardActual*(G67/DrawWeightSum),2),IF(A67=BuildStart+BuildMonths-1,HardActual-SUM(H$65:H66),0)) | I67: =IF(A67=0,SoftActual,0)+H67 | J67: =O66 | K67: =P66 | L67: =MIN(I67,MAX(0,EquityReq-J67)) | M67: =MIN(I67-L67,Commitment-K67) | N67: =L67+(I67-L67-M67) | O67: =J67+I67 | P67: =K67+M67 | Q67: =W66 | R67: =IF(AND(A67=BuildStart,Commitment>0),ConstrPoints,0) | S67: =IF(M67>0,DrawFee,0) | T67: =ROUND(Q67*LoanRate/12*B67,2) | U67: =IF(CapFlag=1,0,T67) | V67: =IF(CapFlag=1,T67,0) | W67: =Q67+M67+V67 | X67: =ROUND(LandLoan*LandRate/12*C67,2) | Y67: =COUNTIF(colExtPeriod,A67)*ExtFee | Z67: =ROUND(TaxRate/12*(LandPrice+O67)*C67,2) | AA67: =ROUND(InsuranceRate/12*EstimateTotal*B67,2) | AB67: =ROUND(UtilBuild*D67+UtilAfter*E67,2) | AC67: =ROUND(StagingMonthly*F67,2) | AD67: =ROUND(UpkeepMonthly*E67,2) | AE67: =ROUND(HoaMonthly*C67,2) | AF67: =IF(A67=0,LandPrice-LandLoan+LandClosing+LandPoints,0) | AG67: =AF67+N67+R67+S67+U67+X67+Y67+Z67+AA67+AB67+AC67+AD67+AE67 | AH67: =AH66+AG67 | AJ67: =A67 | AK67: =IF(AJ67<ExtCount,INT(Maturity+AJ67*ExtensionMonths),"")
A68: =A67+1 | B68: =MAX(0,MIN(A68+1,SaleClose)-MAX(A68,BuildStart)) | C68: =MAX(0,MIN(A68+1,SaleClose)-MAX(A68,0)) | D68: =MAX(0,MIN(A68+1,Completion)-MAX(A68,BuildStart)) | E68: =MAX(0,MIN(A68+1,SaleClose)-MAX(A68,Completion)) | F68: =MAX(0,MIN(A68+1,Contract)-MAX(A68,ListMonth)) | G68: =IF(AND(A68>=BuildStart,A68<BuildStart+BuildMonths),SIN(PI()*(A68-BuildStart+0.5)/BuildMonths),0) | H68: =IF(AND(A68>=BuildStart,A68<BuildStart+BuildMonths-1),ROUND(HardActual*(G68/DrawWeightSum),2),IF(A68=BuildStart+BuildMonths-1,HardActual-SUM(H$65:H67),0)) | I68: =IF(A68=0,SoftActual,0)+H68 | J68: =O67 | K68: =P67 | L68: =MIN(I68,MAX(0,EquityReq-J68)) | M68: =MIN(I68-L68,Commitment-K68) | N68: =L68+(I68-L68-M68) | O68: =J68+I68 | P68: =K68+M68 | Q68: =W67 | R68: =IF(AND(A68=BuildStart,Commitment>0),ConstrPoints,0) | S68: =IF(M68>0,DrawFee,0) | T68: =ROUND(Q68*LoanRate/12*B68,2) | U68: =IF(CapFlag=1,0,T68) | V68: =IF(CapFlag=1,T68,0) | W68: =Q68+M68+V68 | X68: =ROUND(LandLoan*LandRate/12*C68,2) | Y68: =COUNTIF(colExtPeriod,A68)*ExtFee | Z68: =ROUND(TaxRate/12*(LandPrice+O68)*C68,2) | AA68: =ROUND(InsuranceRate/12*EstimateTotal*B68,2) | AB68: =ROUND(UtilBuild*D68+UtilAfter*E68,2) | AC68: =ROUND(StagingMonthly*F68,2) | AD68: =ROUND(UpkeepMonthly*E68,2) | AE68: =ROUND(HoaMonthly*C68,2) | AF68: =IF(A68=0,LandPrice-LandLoan+LandClosing+LandPoints,0) | AG68: =AF68+N68+R68+S68+U68+X68+Y68+Z68+AA68+AB68+AC68+AD68+AE68 | AH68: =AH67+AG68 | AJ68: =A68 | AK68: =IF(AJ68<ExtCount,INT(Maturity+AJ68*ExtensionMonths),"")
A69: =A68+1 | B69: =MAX(0,MIN(A69+1,SaleClose)-MAX(A69,BuildStart)) | C69: =MAX(0,MIN(A69+1,SaleClose)-MAX(A69,0)) | D69: =MAX(0,MIN(A69+1,Completion)-MAX(A69,BuildStart)) | E69: =MAX(0,MIN(A69+1,SaleClose)-MAX(A69,Completion)) | F69: =MAX(0,MIN(A69+1,Contract)-MAX(A69,ListMonth)) | G69: =IF(AND(A69>=BuildStart,A69<BuildStart+BuildMonths),SIN(PI()*(A69-BuildStart+0.5)/BuildMonths),0) | H69: =IF(AND(A69>=BuildStart,A69<BuildStart+BuildMonths-1),ROUND(HardActual*(G69/DrawWeightSum),2),IF(A69=BuildStart+BuildMonths-1,HardActual-SUM(H$65:H68),0)) | I69: =IF(A69=0,SoftActual,0)+H69 | J69: =O68 | K69: =P68 | L69: =MIN(I69,MAX(0,EquityReq-J69)) | M69: =MIN(I69-L69,Commitment-K69) | N69: =L69+(I69-L69-M69) | O69: =J69+I69 | P69: =K69+M69 | Q69: =W68 | R69: =IF(AND(A69=BuildStart,Commitment>0),ConstrPoints,0) | S69: =IF(M69>0,DrawFee,0) | T69: =ROUND(Q69*LoanRate/12*B69,2) | U69: =IF(CapFlag=1,0,T69) | V69: =IF(CapFlag=1,T69,0) | W69: =Q69+M69+V69 | X69: =ROUND(LandLoan*LandRate/12*C69,2) | Y69: =COUNTIF(colExtPeriod,A69)*ExtFee | Z69: =ROUND(TaxRate/12*(LandPrice+O69)*C69,2) | AA69: =ROUND(InsuranceRate/12*EstimateTotal*B69,2) | AB69: =ROUND(UtilBuild*D69+UtilAfter*E69,2) | AC69: =ROUND(StagingMonthly*F69,2) | AD69: =ROUND(UpkeepMonthly*E69,2) | AE69: =ROUND(HoaMonthly*C69,2) | AF69: =IF(A69=0,LandPrice-LandLoan+LandClosing+LandPoints,0) | AG69: =AF69+N69+R69+S69+U69+X69+Y69+Z69+AA69+AB69+AC69+AD69+AE69 | AH69: =AH68+AG69 | AJ69: =A69 | AK69: =IF(AJ69<ExtCount,INT(Maturity+AJ69*ExtensionMonths),"")
A70: =A69+1 | B70: =MAX(0,MIN(A70+1,SaleClose)-MAX(A70,BuildStart)) | C70: =MAX(0,MIN(A70+1,SaleClose)-MAX(A70,0)) | D70: =MAX(0,MIN(A70+1,Completion)-MAX(A70,BuildStart)) | E70: =MAX(0,MIN(A70+1,SaleClose)-MAX(A70,Completion)) | F70: =MAX(0,MIN(A70+1,Contract)-MAX(A70,ListMonth)) | G70: =IF(AND(A70>=BuildStart,A70<BuildStart+BuildMonths),SIN(PI()*(A70-BuildStart+0.5)/BuildMonths),0) | H70: =IF(AND(A70>=BuildStart,A70<BuildStart+BuildMonths-1),ROUND(HardActual*(G70/DrawWeightSum),2),IF(A70=BuildStart+BuildMonths-1,HardActual-SUM(H$65:H69),0)) | I70: =IF(A70=0,SoftActual,0)+H70 | J70: =O69 | K70: =P69 | L70: =MIN(I70,MAX(0,EquityReq-J70)) | M70: =MIN(I70-L70,Commitment-K70) | N70: =L70+(I70-L70-M70) | O70: =J70+I70 | P70: =K70+M70 | Q70: =W69 | R70: =IF(AND(A70=BuildStart,Commitment>0),ConstrPoints,0) | S70: =IF(M70>0,DrawFee,0) | T70: =ROUND(Q70*LoanRate/12*B70,2) | U70: =IF(CapFlag=1,0,T70) | V70: =IF(CapFlag=1,T70,0) | W70: =Q70+M70+V70 | X70: =ROUND(LandLoan*LandRate/12*C70,2) | Y70: =COUNTIF(colExtPeriod,A70)*ExtFee | Z70: =ROUND(TaxRate/12*(LandPrice+O70)*C70,2) | AA70: =ROUND(InsuranceRate/12*EstimateTotal*B70,2) | AB70: =ROUND(UtilBuild*D70+UtilAfter*E70,2) | AC70: =ROUND(StagingMonthly*F70,2) | AD70: =ROUND(UpkeepMonthly*E70,2) | AE70: =ROUND(HoaMonthly*C70,2) | AF70: =IF(A70=0,LandPrice-LandLoan+LandClosing+LandPoints,0) | AG70: =AF70+N70+R70+S70+U70+X70+Y70+Z70+AA70+AB70+AC70+AD70+AE70 | AH70: =AH69+AG70 | AJ70: =A70 | AK70: =IF(AJ70<ExtCount,INT(Maturity+AJ70*ExtensionMonths),"")
A71: =A70+1 | B71: =MAX(0,MIN(A71+1,SaleClose)-MAX(A71,BuildStart)) | C71: =MAX(0,MIN(A71+1,SaleClose)-MAX(A71,0)) | D71: =MAX(0,MIN(A71+1,Completion)-MAX(A71,BuildStart)) | E71: =MAX(0,MIN(A71+1,SaleClose)-MAX(A71,Completion)) | F71: =MAX(0,MIN(A71+1,Contract)-MAX(A71,ListMonth)) | G71: =IF(AND(A71>=BuildStart,A71<BuildStart+BuildMonths),SIN(PI()*(A71-BuildStart+0.5)/BuildMonths),0) | H71: =IF(AND(A71>=BuildStart,A71<BuildStart+BuildMonths-1),ROUND(HardActual*(G71/DrawWeightSum),2),IF(A71=BuildStart+BuildMonths-1,HardActual-SUM(H$65:H70),0)) | I71: =IF(A71=0,SoftActual,0)+H71 | J71: =O70 | K71: =P70 | L71: =MIN(I71,MAX(0,EquityReq-J71)) | M71: =MIN(I71-L71,Commitment-K71) | N71: =L71+(I71-L71-M71) | O71: =J71+I71 | P71: =K71+M71 | Q71: =W70 | R71: =IF(AND(A71=BuildStart,Commitment>0),ConstrPoints,0) | S71: =IF(M71>0,DrawFee,0) | T71: =ROUND(Q71*LoanRate/12*B71,2) | U71: =IF(CapFlag=1,0,T71) | V71: =IF(CapFlag=1,T71,0) | W71: =Q71+M71+V71 | X71: =ROUND(LandLoan*LandRate/12*C71,2) | Y71: =COUNTIF(colExtPeriod,A71)*ExtFee | Z71: =ROUND(TaxRate/12*(LandPrice+O71)*C71,2) | AA71: =ROUND(InsuranceRate/12*EstimateTotal*B71,2) | AB71: =ROUND(UtilBuild*D71+UtilAfter*E71,2) | AC71: =ROUND(StagingMonthly*F71,2) | AD71: =ROUND(UpkeepMonthly*E71,2) | AE71: =ROUND(HoaMonthly*C71,2) | AF71: =IF(A71=0,LandPrice-LandLoan+LandClosing+LandPoints,0) | AG71: =AF71+N71+R71+S71+U71+X71+Y71+Z71+AA71+AB71+AC71+AD71+AE71 | AH71: =AH70+AG71 | AJ71: =A71 | AK71: =IF(AJ71<ExtCount,INT(Maturity+AJ71*ExtensionMonths),"")
A72: =A71+1 | B72: =MAX(0,MIN(A72+1,SaleClose)-MAX(A72,BuildStart)) | C72: =MAX(0,MIN(A72+1,SaleClose)-MAX(A72,0)) | D72: =MAX(0,MIN(A72+1,Completion)-MAX(A72,BuildStart)) | E72: =MAX(0,MIN(A72+1,SaleClose)-MAX(A72,Completion)) | F72: =MAX(0,MIN(A72+1,Contract)-MAX(A72,ListMonth)) | G72: =IF(AND(A72>=BuildStart,A72<BuildStart+BuildMonths),SIN(PI()*(A72-BuildStart+0.5)/BuildMonths),0) | H72: =IF(AND(A72>=BuildStart,A72<BuildStart+BuildMonths-1),ROUND(HardActual*(G72/DrawWeightSum),2),IF(A72=BuildStart+BuildMonths-1,HardActual-SUM(H$65:H71),0)) | I72: =IF(A72=0,SoftActual,0)+H72 | J72: =O71 | K72: =P71 | L72: =MIN(I72,MAX(0,EquityReq-J72)) | M72: =MIN(I72-L72,Commitment-K72) | N72: =L72+(I72-L72-M72) | O72: =J72+I72 | P72: =K72+M72 | Q72: =W71 | R72: =IF(AND(A72=BuildStart,Commitment>0),ConstrPoints,0) | S72: =IF(M72>0,DrawFee,0) | T72: =ROUND(Q72*LoanRate/12*B72,2) | U72: =IF(CapFlag=1,0,T72) | V72: =IF(CapFlag=1,T72,0) | W72: =Q72+M72+V72 | X72: =ROUND(LandLoan*LandRate/12*C72,2) | Y72: =COUNTIF(colExtPeriod,A72)*ExtFee | Z72: =ROUND(TaxRate/12*(LandPrice+O72)*C72,2) | AA72: =ROUND(InsuranceRate/12*EstimateTotal*B72,2) | AB72: =ROUND(UtilBuild*D72+UtilAfter*E72,2) | AC72: =ROUND(StagingMonthly*F72,2) | AD72: =ROUND(UpkeepMonthly*E72,2) | AE72: =ROUND(HoaMonthly*C72,2) | AF72: =IF(A72=0,LandPrice-LandLoan+LandClosing+LandPoints,0) | AG72: =AF72+N72+R72+S72+U72+X72+Y72+Z72+AA72+AB72+AC72+AD72+AE72 | AH72: =AH71+AG72 | AJ72: =A72 | AK72: =IF(AJ72<ExtCount,INT(Maturity+AJ72*ExtensionMonths),"")
A73: =A72+1 | B73: =MAX(0,MIN(A73+1,SaleClose)-MAX(A73,BuildStart)) | C73: =MAX(0,MIN(A73+1,SaleClose)-MAX(A73,0)) | D73: =MAX(0,MIN(A73+1,Completion)-MAX(A73,BuildStart)) | E73: =MAX(0,MIN(A73+1,SaleClose)-MAX(A73,Completion)) | F73: =MAX(0,MIN(A73+1,Contract)-MAX(A73,ListMonth)) | G73: =IF(AND(A73>=BuildStart,A73<BuildStart+BuildMonths),SIN(PI()*(A73-BuildStart+0.5)/BuildMonths),0) | H73: =IF(AND(A73>=BuildStart,A73<BuildStart+BuildMonths-1),ROUND(HardActual*(G73/DrawWeightSum),2),IF(A73=BuildStart+BuildMonths-1,HardActual-SUM(H$65:H72),0)) | I73: =IF(A73=0,SoftActual,0)+H73 | J73: =O72 | K73: =P72 | L73: =MIN(I73,MAX(0,EquityReq-J73)) | M73: =MIN(I73-L73,Commitment-K73) | N73: =L73+(I73-L73-M73) | O73: =J73+I73 | P73: =K73+M73 | Q73: =W72 | R73: =IF(AND(A73=BuildStart,Commitment>0),ConstrPoints,0) | S73: =IF(M73>0,DrawFee,0) | T73: =ROUND(Q73*LoanRate/12*B73,2) | U73: =IF(CapFlag=1,0,T73) | V73: =IF(CapFlag=1,T73,0) | W73: =Q73+M73+V73 | X73: =ROUND(LandLoan*LandRate/12*C73,2) | Y73: =COUNTIF(colExtPeriod,A73)*ExtFee | Z73: =ROUND(TaxRate/12*(LandPrice+O73)*C73,2) | AA73: =ROUND(InsuranceRate/12*EstimateTotal*B73,2) | AB73: =ROUND(UtilBuild*D73+UtilAfter*E73,2) | AC73: =ROUND(StagingMonthly*F73,2) | AD73: =ROUND(UpkeepMonthly*E73,2) | AE73: =ROUND(HoaMonthly*C73,2) | AF73: =IF(A73=0,LandPrice-LandLoan+LandClosing+LandPoints,0) | AG73: =AF73+N73+R73+S73+U73+X73+Y73+Z73+AA73+AB73+AC73+AD73+AE73 | AH73: =AH72+AG73 | AJ73: =A73 | AK73: =IF(AJ73<ExtCount,INT(Maturity+AJ73*ExtensionMonths),"")
A74: =A73+1 | B74: =MAX(0,MIN(A74+1,SaleClose)-MAX(A74,BuildStart)) | C74: =MAX(0,MIN(A74+1,SaleClose)-MAX(A74,0)) | D74: =MAX(0,MIN(A74+1,Completion)-MAX(A74,BuildStart)) | E74: =MAX(0,MIN(A74+1,SaleClose)-MAX(A74,Completion)) | F74: =MAX(0,MIN(A74+1,Contract)-MAX(A74,ListMonth)) | G74: =IF(AND(A74>=BuildStart,A74<BuildStart+BuildMonths),SIN(PI()*(A74-BuildStart+0.5)/BuildMonths),0) | H74: =IF(AND(A74>=BuildStart,A74<BuildStart+BuildMonths-1),ROUND(HardActual*(G74/DrawWeightSum),2),IF(A74=BuildStart+BuildMonths-1,HardActual-SUM(H$65:H73),0)) | I74: =IF(A74=0,SoftActual,0)+H74 | J74: =O73 | K74: =P73 | L74: =MIN(I74,MAX(0,EquityReq-J74)) | M74: =MIN(I74-L74,Commitment-K74) | N74: =L74+(I74-L74-M74) | O74: =J74+I74 | P74: =K74+M74 | Q74: =W73 | R74: =IF(AND(A74=BuildStart,Commitment>0),ConstrPoints,0) | S74: =IF(M74>0,DrawFee,0) | T74: =ROUND(Q74*LoanRate/12*B74,2) | U74: =IF(CapFlag=1,0,T74) | V74: =IF(CapFlag=1,T74,0) | W74: =Q74+M74+V74 | X74: =ROUND(LandLoan*LandRate/12*C74,2) | Y74: =COUNTIF(colExtPeriod,A74)*ExtFee | Z74: =ROUND(TaxRate/12*(LandPrice+O74)*C74,2) | AA74: =ROUND(InsuranceRate/12*EstimateTotal*B74,2) | AB74: =ROUND(UtilBuild*D74+UtilAfter*E74,2) | AC74: =ROUND(StagingMonthly*F74,2) | AD74: =ROUND(UpkeepMonthly*E74,2) | AE74: =ROUND(HoaMonthly*C74,2) | AF74: =IF(A74=0,LandPrice-LandLoan+LandClosing+LandPoints,0) | AG74: =AF74+N74+R74+S74+U74+X74+Y74+Z74+AA74+AB74+AC74+AD74+AE74 | AH74: =AH73+AG74 | AJ74: =A74 | AK74: =IF(AJ74<ExtCount,INT(Maturity+AJ74*ExtensionMonths),"")
A75: =A74+1 | B75: =MAX(0,MIN(A75+1,SaleClose)-MAX(A75,BuildStart)) | C75: =MAX(0,MIN(A75+1,SaleClose)-MAX(A75,0)) | D75: =MAX(0,MIN(A75+1,Completion)-MAX(A75,BuildStart)) | E75: =MAX(0,MIN(A75+1,SaleClose)-MAX(A75,Completion)) | F75: =MAX(0,MIN(A75+1,Contract)-MAX(A75,ListMonth)) | G75: =IF(AND(A75>=BuildStart,A75<BuildStart+BuildMonths),SIN(PI()*(A75-BuildStart+0.5)/BuildMonths),0) | H75: =IF(AND(A75>=BuildStart,A75<BuildStart+BuildMonths-1),ROUND(HardActual*(G75/DrawWeightSum),2),IF(A75=BuildStart+BuildMonths-1,HardActual-SUM(H$65:H74),0)) | I75: =IF(A75=0,SoftActual,0)+H75 | J75: =O74 | K75: =P74 | L75: =MIN(I75,MAX(0,EquityReq-J75)) | M75: =MIN(I75-L75,Commitment-K75) | N75: =L75+(I75-L75-M75) | O75: =J75+I75 | P75: =K75+M75 | Q75: =W74 | R75: =IF(AND(A75=BuildStart,Commitment>0),ConstrPoints,0) | S75: =IF(M75>0,DrawFee,0) | T75: =ROUND(Q75*LoanRate/12*B75,2) | U75: =IF(CapFlag=1,0,T75) | V75: =IF(CapFlag=1,T75,0) | W75: =Q75+M75+V75 | X75: =ROUND(LandLoan*LandRate/12*C75,2) | Y75: =COUNTIF(colExtPeriod,A75)*ExtFee | Z75: =ROUND(TaxRate/12*(LandPrice+O75)*C75,2) | AA75: =ROUND(InsuranceRate/12*EstimateTotal*B75,2) | AB75: =ROUND(UtilBuild*D75+UtilAfter*E75,2) | AC75: =ROUND(StagingMonthly*F75,2) | AD75: =ROUND(UpkeepMonthly*E75,2) | AE75: =ROUND(HoaMonthly*C75,2) | AF75: =IF(A75=0,LandPrice-LandLoan+LandClosing+LandPoints,0) | AG75: =AF75+N75+R75+S75+U75+X75+Y75+Z75+AA75+AB75+AC75+AD75+AE75 | AH75: =AH74+AG75 | AJ75: =A75 | AK75: =IF(AJ75<ExtCount,INT(Maturity+AJ75*ExtensionMonths),"")
A76: =A75+1 | B76: =MAX(0,MIN(A76+1,SaleClose)-MAX(A76,BuildStart)) | C76: =MAX(0,MIN(A76+1,SaleClose)-MAX(A76,0)) | D76: =MAX(0,MIN(A76+1,Completion)-MAX(A76,BuildStart)) | E76: =MAX(0,MIN(A76+1,SaleClose)-MAX(A76,Completion)) | F76: =MAX(0,MIN(A76+1,Contract)-MAX(A76,ListMonth)) | G76: =IF(AND(A76>=BuildStart,A76<BuildStart+BuildMonths),SIN(PI()*(A76-BuildStart+0.5)/BuildMonths),0) | H76: =IF(AND(A76>=BuildStart,A76<BuildStart+BuildMonths-1),ROUND(HardActual*(G76/DrawWeightSum),2),IF(A76=BuildStart+BuildMonths-1,HardActual-SUM(H$65:H75),0)) | I76: =IF(A76=0,SoftActual,0)+H76 | J76: =O75 | K76: =P75 | L76: =MIN(I76,MAX(0,EquityReq-J76)) | M76: =MIN(I76-L76,Commitment-K76) | N76: =L76+(I76-L76-M76) | O76: =J76+I76 | P76: =K76+M76 | Q76: =W75 | R76: =IF(AND(A76=BuildStart,Commitment>0),ConstrPoints,0) | S76: =IF(M76>0,DrawFee,0) | T76: =ROUND(Q76*LoanRate/12*B76,2) | U76: =IF(CapFlag=1,0,T76) | V76: =IF(CapFlag=1,T76,0) | W76: =Q76+M76+V76 | X76: =ROUND(LandLoan*LandRate/12*C76,2) | Y76: =COUNTIF(colExtPeriod,A76)*ExtFee | Z76: =ROUND(TaxRate/12*(LandPrice+O76)*C76,2) | AA76: =ROUND(InsuranceRate/12*EstimateTotal*B76,2) | AB76: =ROUND(UtilBuild*D76+UtilAfter*E76,2) | AC76: =ROUND(StagingMonthly*F76,2) | AD76: =ROUND(UpkeepMonthly*E76,2) | AE76: =ROUND(HoaMonthly*C76,2) | AF76: =IF(A76=0,LandPrice-LandLoan+LandClosing+LandPoints,0) | AG76: =AF76+N76+R76+S76+U76+X76+Y76+Z76+AA76+AB76+AC76+AD76+AE76 | AH76: =AH75+AG76 | AJ76: =A76 | AK76: =IF(AJ76<ExtCount,INT(Maturity+AJ76*ExtensionMonths),"")
A77: =A76+1 | B77: =MAX(0,MIN(A77+1,SaleClose)-MAX(A77,BuildStart)) | C77: =MAX(0,MIN(A77+1,SaleClose)-MAX(A77,0)) | D77: =MAX(0,MIN(A77+1,Completion)-MAX(A77,BuildStart)) | E77: =MAX(0,MIN(A77+1,SaleClose)-MAX(A77,Completion)) | F77: =MAX(0,MIN(A77+1,Contract)-MAX(A77,ListMonth)) | G77: =IF(AND(A77>=BuildStart,A77<BuildStart+BuildMonths),SIN(PI()*(A77-BuildStart+0.5)/BuildMonths),0) | H77: =IF(AND(A77>=BuildStart,A77<BuildStart+BuildMonths-1),ROUND(HardActual*(G77/DrawWeightSum),2),IF(A77=BuildStart+BuildMonths-1,HardActual-SUM(H$65:H76),0)) | I77: =IF(A77=0,SoftActual,0)+H77 | J77: =O76 | K77: =P76 | L77: =MIN(I77,MAX(0,EquityReq-J77)) | M77: =MIN(I77-L77,Commitment-K77) | N77: =L77+(I77-L77-M77) | O77: =J77+I77 | P77: =K77+M77 | Q77: =W76 | R77: =IF(AND(A77=BuildStart,Commitment>0),ConstrPoints,0) | S77: =IF(M77>0,DrawFee,0) | T77: =ROUND(Q77*LoanRate/12*B77,2) | U77: =IF(CapFlag=1,0,T77) | V77: =IF(CapFlag=1,T77,0) | W77: =Q77+M77+V77 | X77: =ROUND(LandLoan*LandRate/12*C77,2) | Y77: =COUNTIF(colExtPeriod,A77)*ExtFee | Z77: =ROUND(TaxRate/12*(LandPrice+O77)*C77,2) | AA77: =ROUND(InsuranceRate/12*EstimateTotal*B77,2) | AB77: =ROUND(UtilBuild*D77+UtilAfter*E77,2) | AC77: =ROUND(StagingMonthly*F77,2) | AD77: =ROUND(UpkeepMonthly*E77,2) | AE77: =ROUND(HoaMonthly*C77,2) | AF77: =IF(A77=0,LandPrice-LandLoan+LandClosing+LandPoints,0) | AG77: =AF77+N77+R77+S77+U77+X77+Y77+Z77+AA77+AB77+AC77+AD77+AE77 | AH77: =AH76+AG77 | AJ77: =A77 | AK77: =IF(AJ77<ExtCount,INT(Maturity+AJ77*ExtensionMonths),"")
... A90: =A89+1 | B90: =MAX(0,MIN(A90+1,SaleClose)-MAX(A90,BuildStart)) | C90: =MAX(0,MIN(A90+1,SaleClose)-MAX(A90,0)) | D90: =MAX(0,MIN(A90+1,Completion)-MAX(A90,BuildStart)) | E90: =MAX(0,MIN(A90+1,SaleClose)-MAX(A90,Completion)) | F90: =MAX(0,MIN(A90+1,Contract)-MAX(A90,ListMonth)) | G90: =IF(AND(A90>=BuildStart,A90<BuildStart+BuildMonths),SIN(PI()*(A90-BuildStart+0.5)/BuildMonths),0) | H90: =IF(AND(A90>=BuildStart,A90<BuildStart+BuildMonths-1),ROUND(HardActual*(G90/DrawWeightSum),2),IF(A90=BuildStart+BuildMonths-1,HardActual-SUM(H$65:H89),0)) | I90: =IF(A90=0,SoftActual,0)+H90 | J90: =O89 | K90: =P89 | L90: =MIN(I90,MAX(0,EquityReq-J90)) | M90: =MIN(I90-L90,Commitment-K90) | N90: =L90+(I90-L90-M90) | O90: =J90+I90 | P90: =K90+M90 | Q90: =W89 | R90: =IF(AND(A90=BuildStart,Commitment>0),ConstrPoints,0) | S90: =IF(M90>0,DrawFee,0) | T90: =ROUND(Q90*LoanRate/12*B90,2) | U90: =IF(CapFlag=1,0,T90) | V90: =IF(CapFlag=1,T90,0) | W90: =Q90+M90+V90 | X90: =ROUND(LandLoan*LandRate/12*C90,2) | Y90: =COUNTIF(colExtPeriod,A90)*ExtFee | Z90: =ROUND(TaxRate/12*(LandPrice+O90)*C90,2) | AA90: =ROUND(InsuranceRate/12*EstimateTotal*B90,2) | AB90: =ROUND(UtilBuild*D90+UtilAfter*E90,2) | AC90: =ROUND(StagingMonthly*F90,2) | AD90: =ROUND(UpkeepMonthly*E90,2) | AE90: =ROUND(HoaMonthly*C90,2) | AF90: =IF(A90=0,LandPrice-LandLoan+LandClosing+LandPoints,0) | AG90: =AF90+N90+R90+S90+U90+X90+Y90+Z90+AA90+AB90+AC90+AD90+AE90 | AH90: =AH89+AG90 | AJ90: =A90 | AK90: =IF(AJ90<ExtCount,INT(Maturity+AJ90*ExtensionMonths),"")
